flake8_copyright.py
flake8_copyright-0.2.4.dist-info/COPYING
flake8_copyright-0.2.4.dist-info/COPYING.LESSER
flake8_copyright-0.2.4.dist-info/METADATA
flake8_copyright-0.2.4.dist-info/WHEEL
flake8_copyright-0.2.4.dist-info/entry_points.txt
flake8_copyright-0.2.4.dist-info/top_level.txt
flake8_copyright-0.2.4.dist-info/RECORD
