Metadata-Version: 2.1
Name: flake8-copyright
Version: 0.2.4
Summary: Adds copyright checks to flake8
Home-page: https://github.com/savoirfairelinux/flake8-copyright
Author: Virgil Dupras
Author-email: virgil.dupras@savoirfairelinux.com
License: UNKNOWN
Keywords: pep8 flake8 copyright
Platform: UNKNOWN
Classifier: Programming Language :: Python
Classifier: Programming Language :: Python :: 2
Classifier: Programming Language :: Python :: 3
Requires-Dist: setuptools
